net_parser/__init__.py
net_parser/exceptions.py
net_parser/config/BaseConfigLine.py
net_parser/config/BaseConfigParser.py
net_parser/config/ConfigDiff.py
net_parser/config/IosConfigParser.py
net_parser/config/IosInterfaceParser.py
net_parser/config/IosSectionParsers.py
net_parser/config/__init__.py
net_parser/connections/BaseConnections.py
net_parser/connections/__init__.py
net_parser/ops/BaseOpsParsers.py
net_parser/ops/__init__.py
net_parser/ops/ios/IosOpsParser.py
net_parser/ops/ios/__init__.py
net_parser/ops/models/BaseOpsModels.py
net_parser/ops/models/__init__.py
net_parser/utils/__init__.py
net_parser/utils/common.py
net_parser/utils/get_logger.py
tests/__init__.py
tests/dont_test_BaseConnections.py
tests/test_BaseConfigLine.py
tests/test_BaseConfigParser.py
tests/test_BaseOpsParser.py
tests/test_ConfigDiff.py
tests/test_IosConfigParser.py
tests/test_IosSectionParsers.py
tests/test_Utils.py
net_parser-0.3.1.dist-info/LICENSE
net_parser-0.3.1.dist-info/METADATA
net_parser-0.3.1.dist-info/WHEEL
net_parser-0.3.1.dist-info/top_level.txt
net_parser-0.3.1.dist-info/RECORD
