Metadata-Version: 2.1
Name: net-parser
Version: 0.3.1
Summary: Network Config Parser
Home-page: UNKNOWN
Author: Miroslav Hudec <http://github.com/mihudec>
License: UNKNOWN
Platform: UNKNOWN
License-File: LICENSE
Requires-Dist: net-models (>=0.3.1)
